flake8_bbs/__init__.py
flake8_bbs/checker.py
flake8_bbs-0.1.0a3.dist-info/entry_points.txt
flake8_bbs-0.1.0a3.dist-info/LICENSE
flake8_bbs-0.1.0a3.dist-info/WHEEL
flake8_bbs-0.1.0a3.dist-info/METADATA
flake8_bbs-0.1.0a3.dist-info/RECORD
