Metadata-Version: 2.1
Name: flake8-bbs
Version: 0.1.0a3
Summary: A flake8 extension that checks blank lines before statements
Home-page: https://github.com/ts-mk/flake8-bbs/
License: MIT
Author: Tomas Mrozek
Author-email: tm@nohup.run
Maintainer: Tomas Mrozek
Maintainer-email: tm@nohup.run
Requires-Python: >=3.8
Classifier: Environment :: Console
Classifier: Framework :: Flake8
Classifier: License :: OSI Approved :: MIT License
Classifier: Operating System :: OS Independent
Classifier: Programming Language :: Python
Classifier: Programming Language :: Python :: 3
Classifier: Programming Language :: Python :: 3.10
Classifier: Programming Language :: Python :: 3.11
Classifier: Programming Language :: Python :: 3.8
Classifier: Programming Language :: Python :: 3.9
Classifier: Topic :: Software Development :: Documentation
Classifier: Topic :: Software Development :: Libraries :: Python Modules
Classifier: Topic :: Software Development :: Quality Assurance
Requires-Dist: flake8 (>=3.8.0)
Project-URL: Documentation, https://github.com/ts-mk/flake8-bbs/blob/master/README.md
Project-URL: Repository, https://github.com/ts-mk/flake8-bbs/
